LICENSE
MANIFEST.in
README.md
requirements.txt
setup.py
dodo/__init__.py
dodo/__main__.py
dodo/dodo.py
dodo_desktop_switcher.egg-info/PKG-INFO
dodo_desktop_switcher.egg-info/SOURCES.txt
dodo_desktop_switcher.egg-info/dependency_links.txt
dodo_desktop_switcher.egg-info/entry_points.txt
dodo_desktop_switcher.egg-info/requires.txt
dodo_desktop_switcher.egg-info/top_level.txt