Metadata-Version: 2.4
Name: dodo-desktop-switcher
Version: 0.2.0
Summary: Dodo: Desktop Switcher for Windows
Home-page: https://github.com/cool-RR/dodo
Author: Ram Rachum
Author-email: ram@rachum.com
Project-URL: Bug Tracker, https://github.com/cool-RR/dodo/issues
Project-URL: Source Code, https://github.com/cool-RR/dodo
Classifier: Development Status :: 4 - Beta
Classifier: Environment :: Win32 (MS Windows)
Classifier: Intended Audience :: End Users/Desktop
Classifier: Operating System :: Microsoft :: Windows :: Windows 10
Classifier: Operating System :: Microsoft :: Windows :: Windows 11
Classifier: Programming Language :: Python :: 3.12
Classifier: Programming Language :: Python :: 3.13
Classifier: Programming Language :: Python :: 3.14
Classifier: Programming Language :: Python :: Implementation :: CPython
Classifier: Topic :: Desktop Environment
Requires-Python: >=3.12
License-File: LICENSE
Requires-Dist: pyvda==0.5.0
Requires-Dist: wxPython==4.2.3
Requires-Dist: pywin32==308
Requires-Dist: PyYAML>=6.0
Requires-Dist: watchdog>=3.0.0
Requires-Dist: click>=8.0.0
Dynamic: author
Dynamic: author-email
Dynamic: classifier
Dynamic: description
Dynamic: description-content-type
Dynamic: home-page
Dynamic: license-file
Dynamic: project-url
Dynamic: requires-dist
Dynamic: requires-python
Dynamic: summary
